<?xml version="1.0" encoding="UTF-8" ?>
<!DOCTYPE tiles-definitions PUBLIC "-//Apache Software Foundation//DTD Tiles Configuration 3.0//EN" "http://tiles.apache.org/dtds/tiles-config_3_0.dtd">

<tiles-definitions>

    <definition name="defaultTemplate" template="/WEB-INF/views/templates/baseTemplate.jsp">
        <put-attribute name="header" value="/WEB-INF/views/templates/header.jsp" />
        <put-attribute name="content" value="/WEB-INF/views/templates/content.jsp"/>
        <put-attribute name="footer" value="/WEB-INF/views/templates/footer.jsp" />
    </definition>


    <definition name="cars" extends="defaultTemplate">
        <!--<put-attribute name="bodyClass" value="home"/>-->
        <put-attribute name="bodyContentClass" value="container"/>
        <put-attribute name="body" value="/WEB-INF/views/pages/cars.jsp"/>
    </definition>

    <definition name="welcome" extends="defaultTemplate">
        <put-attribute name="bodyContentClass" value="container"/>
        <put-attribute name="body" value="/WEB-INF/views/pages/welcome.jsp"/>
    </definition>

    <definition name="carCompay" extends="defaultTemplate">
        <put-attribute name="bodyContentClass" value="container"/>
        <put-attribute name="body" value="/WEB-INF/views/pages/carCompany.jsp"/>
    </definition>

    <definition name="months" extends="defaultTemplate">
        <put-attribute name="bodyContentClass" value="container"/>
        <put-attribute name="body" value="/WEB-INF/views/pages/months.jsp"/>
    </definition>

    <definition name="admin" extends="defaultTemplate">
        <put-attribute name="bodyContentClass" value="container"/>
        <put-attribute name="body" value="/WEB-INF/views/pages/admin.jsp"/>
    </definition>

    <definition name="login" extends="defaultTemplate">
        <put-attribute name="bodyContentClass" value="container"/>
        <put-attribute name="body" value="/WEB-INF/views/pages/login.jsp"/>
    </definition>

    <definition name="ng-carCompany" extends="defaultTemplate">
        <put-attribute name="bodyContentClass" value="container"/>
        <put-attribute name="body" value="/WEB-INF/views/ng-pages/carCompany.jsp"/>
    </definition>


</tiles-definitions>